{
    "camera_id": "cam_01",
    "event_start_time": "2025-11-19T02:03:46.521560",
    "event_end_time": "2025-11-19T02:03:48.093300",
    "video_file": "cam_01_20251119_020339.mp4",
    "log_file": "cam_01_20251119_020339.json",
    "video_path": "C:\\Users\\Jose\\Desktop\\Tesis\\front-end\\urban-sentinel-front\\public\\data\\clips_guardados\\cam_01_20251119_020339.mp4",
    "log_path": "C:\\Users\\Jose\\Desktop\\Tesis\\front-end\\urban-sentinel-front\\public\\data\\logs_eventos\\cam_01_20251119_020339.json",
    "total_logs": 0,
    "logs": []
}